SHDA/SHDA.py
SHDA/__init__.py
SHDA/common/__init__.py
SHDA/common/brokers.py
SHDA/common/exceptions.py
SHDA/common/helpers.py
SHDA-0.0.3.dist-info/METADATA
SHDA-0.0.3.dist-info/WHEEL
SHDA-0.0.3.dist-info/top_level.txt
SHDA-0.0.3.dist-info/RECORD
