Metadata-Version: 2.1
Name: SHDA
Version: 0.0.3
Summary: Home Broker API - Market data downloader
Home-page: https://github.com/franco-lamas/SHDA
Author: Franco Lamas, Marcelo Colom, St1tch
Author-email: francomlamas@gmail.com
License: GPL V3
Keywords: pandas,BYMA,online,downloader,finance
Platform: any
Classifier: License :: OSI Approved :: Apache Software License
Classifier: Development Status :: 3 - Alpha
Classifier: Operating System :: OS Independent
Classifier: Intended Audience :: Developers
Classifier: Topic :: Office/Business :: Financial
Classifier: Topic :: Office/Business :: Financial :: Investment
Classifier: Topic :: Scientific/Engineering :: Interface Engine/Protocol Translator
Classifier: Topic :: Software Development :: Libraries
Classifier: Topic :: Software Development :: Libraries :: Python Modules
Classifier: Programming Language :: Python :: 3
Classifier: Programming Language :: Python :: 3.8
Classifier: Programming Language :: Python :: 3.9
Classifier: Programming Language :: Python :: 3.10
